<?xml version='1.0' encoding='UTF-8'?>
<types:mule xmlns:types="http://www.mulesoft.org/schema/mule/types">
  <types:catalog>
    <types:type name="auto_7f2d0c01-be18-43aa-93e2-fd71fe2a7d36_Input-Payload" format="java">
      <types:shape format="weave" example="weave/autogenerated/7f2d0c01-be18-43aa-93e2-fd71fe2a7d36/Input-Payload.wev" autogeneratedOrigin="8c944e17-36b9-484f-8e70-66a9b1c0d728"><![CDATA[%dw 2.0

type auto_7f2d0c01_be18_43aa_93e2_fd71fe2a7d36_Input_Payload = Any

]]></types:shape>
    </types:type>
    <types:type name="auto_7f2d0c01-be18-43aa-93e2-fd71fe2a7d36_Input-Attributes" format="java">
      <types:shape format="weave" example="weave/autogenerated/7f2d0c01-be18-43aa-93e2-fd71fe2a7d36/Input-Attributes.wev" autogeneratedOrigin="8c944e17-36b9-484f-8e70-66a9b1c0d728"><![CDATA[%dw 2.0

type auto_7f2d0c01_be18_43aa_93e2_fd71fe2a7d36_Input_Attributes = {|
  listenerPath: String, 
  rawRequestPath: String, 
  relativePath: String, 
  maskedRequestPath: String, 
  version: String, 
  scheme: String, 
  method: String, 
  requestUri: String, 
  rawRequestUri: String, 
  queryString: String, 
  localAddress: String, 
  remoteAddress: String, 
  clientCertificate?: java_security_cert_Certificate, 
  queryParams: { _?: String }, 
  uriParams: { _?: String }, 
  requestPath: String, 
  headers: { _?: String }
|} {"typeAlias": "HttpRequestAttributes",
"typeId": "org.mule.extension.http.api.HttpRequestAttributes"}
type java_security_cert_Certificate = {|
  encoded?: Binary, 
  publicKey?: java_security_PublicKey, 
  "type"?: String
|} {"typeAlias": "Certificate",
"typeId": "java.security.cert.Certificate"}
type java_security_PublicKey = {|  |} {"typeAlias": "PublicKey",
"typeId": "java.security.PublicKey"}





]]></types:shape>
    </types:type>
    <types:type name="auto_7f2d0c01-be18-43aa-93e2-fd71fe2a7d36_Output-Payload" format="json">
      <types:shape format="weave" example="weave/autogenerated/7f2d0c01-be18-43aa-93e2-fd71fe2a7d36/Output-Payload.wev" autogeneratedOrigin="8c944e17-36b9-484f-8e70-66a9b1c0d728"><![CDATA[%dw 2.0

type auto_7f2d0c01_be18_43aa_93e2_fd71fe2a7d36_Output_Payload = {|  |}

]]></types:shape>
    </types:type>
    <types:type name="auto_7f2d0c01-be18-43aa-93e2-fd71fe2a7d36_Output-Attributes" format="java">
      <types:shape format="weave" example="weave/autogenerated/7f2d0c01-be18-43aa-93e2-fd71fe2a7d36/Output-Attributes.wev" autogeneratedOrigin="8c944e17-36b9-484f-8e70-66a9b1c0d728"><![CDATA[%dw 2.0

type auto_7f2d0c01_be18_43aa_93e2_fd71fe2a7d36_Output_Attributes = {|
  listenerPath: String, 
  rawRequestPath: String, 
  relativePath: String, 
  maskedRequestPath: String, 
  version: String, 
  scheme: String, 
  method: String, 
  requestUri: String, 
  rawRequestUri: String, 
  queryString: String, 
  localAddress: String, 
  remoteAddress: String, 
  clientCertificate?: java_security_cert_Certificate, 
  queryParams: { _?: String }, 
  uriParams: { _?: String }, 
  requestPath: String, 
  headers: { _?: String }
|} {"typeAlias": "HttpRequestAttributes",
"typeId": "org.mule.extension.http.api.HttpRequestAttributes"}
type java_security_cert_Certificate = {|
  encoded?: Binary, 
  publicKey?: java_security_PublicKey, 
  "type"?: String
|} {"typeAlias": "Certificate",
"typeId": "java.security.cert.Certificate"}
type java_security_PublicKey = {|  |} {"typeAlias": "PublicKey",
"typeId": "java.security.PublicKey"}





]]></types:shape>
    </types:type>
    <types:type name="registrationjson" format="json">
      <types:shape format="weave" example="json/registration-command-model-json.json"><![CDATA[%dw 2.0

type registrationjson = {|
  userName: String, 
  firstName: String, 
  middleName: String, 
  lastName: String, 
  dateOfBirth: String, 
  placeOfBirth: String, 
  birthSex: String, 
  nationality: String, 
  civilStatus: String, 
  spouseMobileNumber: String, 
  spouseFirstName: String, 
  spouseMiddleName: String, 
  spouseLastName: String, 
  currentAddress: String, 
  mobileNumber: String, 
  email: String, 
  identificationType: String, 
  identificationNumber: String, 
  identificationImage: String, 
  selfieWithIdentificationImage: String, 
  selfieImage: String, 
  motherMaidenFirstName: String, 
  motherMaidenMiddleName: String, 
  motherMaidenLastName: String, 
  fatherFirstName: String, 
  fatherMiddleName: String, 
  fatherLastName: String, 
  parentContactNumber: String, 
  employmentStatus: String, 
  occupationName: String, 
  monthlyEarning: String, 
  employerName: String, 
  employerAddress: String, 
  employerContactNumber: String, 
  signatureImage: String, 
  agreeToTermsAndConditions: String
|} {"example": "{\\\"userName\\\":\\\"apple000\\\",\\\"firstName\\\":\\\"PRE\\\",\\\"middleName\\\":\\\"GOJO\\\",\\\"lastName\\\":\\\"SANSK\\\",\\\"dateOfBirth\\\":\\\"1969-03-17\\\",\\\"placeOfBirth\\\":\\\"METRO MANILA\\\",\\\"birthSex\\\":\\\"FEMALE\\\",\\\"nationality\\\":\\\"FILIPINO\\\",\\\"civilStatus\\\":\\\"MARRIED\\\",\\\"spouseMobileNumber\\\":\\\"09123456789\\\",\\\"spouseFirstName\\\":\\\"FRED\\\",\\\"spouseMiddleName\\\":\\\"CLEAR\\\",\\\"spouseLastName\\\":\\\"VEETUR\\\",\\\"currentAddress\\\":\\\"Escopa, Project 4, District 2, Quezon City, NCR, Philippines\\\",\\\"mobileNumber\\\":\\\"091234567777\\\",\\\"email\\\":\\\"HUAWEI.NOVA3I.YR18@gmail.com\\\",\\\"identificationType\\\":\\\"SSS\\\",\\\"identificationNumber\\\":\\\"1231231321\\\",\\\"identificationImage\\\":\\\"0x0012312313asdasadsasd\\\",\\\"selfieWithIdentificationImage\\\":\\\"0x0aabb233000ads12\\\",\\\"selfieImage\\\":\\\"0x0aasasdadd\\\",\\\"motherMaidenFirstName\\\":\\\"RITA\\\",\\\"motherMaidenMiddleName\\\":\\\"MAQUINYANA\\\",\\\"motherMaidenLastName\\\":\\\"GOJO\\\",\\\"fatherFirstName\\\":\\\"ARN\\\",\\\"fatherMiddleName\\\":\\\"MAIS\\\",\\\"fatherLastName\\\":\\\"GO\\\",\\\"parentContactNumber\\\":\\\"0923123123\\\",\\\"employmentStatus\\\":\\\"PRIVATE EMPLOYEE\\\",\\\"occupationName\\\":\\\"IT STAFF\\\",\\\"monthlyEarning\\\":\\\"10256.00\\\",\\\"employerName\\\":\\\"Collabera Technologies Private Limited Inc\\\",\\\"employerAddress\\\":\\\"6784, Rufino Pacific Tower, 1229 Ayala Ave, Legazpi Village, Makati, 1229 Metro Manila\\\",\\\"employerContactNumber\\\":\\\"(02) 7954 1512\\\",\\\"signatureImage\\\":\\\"0x12312313dasfadg\\\",\\\"agreeToTermsAndConditions\\\":\\\"Y\\\"}"}

]]></types:shape>
    </types:type>
  </types:catalog>
  <types:enrichment select="#7f2d0c01-be18-43aa-93e2-fd71fe2a7d36">
    <types:processor-declaration>
      <types:input-event>
        <types:message>
          <types:payload type="auto_7f2d0c01-be18-43aa-93e2-fd71fe2a7d36_Input-Payload"/>
          <types:attributes type="auto_7f2d0c01-be18-43aa-93e2-fd71fe2a7d36_Input-Attributes"/>
        </types:message>
      </types:input-event>
      <types:output-event>
        <types:message>
          <types:payload type="auto_7f2d0c01-be18-43aa-93e2-fd71fe2a7d36_Output-Payload"/>
          <types:attributes type="auto_7f2d0c01-be18-43aa-93e2-fd71fe2a7d36_Output-Attributes"/>
        </types:message>
      </types:output-event>
    </types:processor-declaration>
  </types:enrichment>
  <types:enrichment select="#b5d24e3a-d181-471c-bcb1-7387889caa20">
    <types:processor-declaration>
      <types:input-event>
        <types:message>
          <types:payload type="registrationjson"/>
        </types:message>
      </types:input-event>
    </types:processor-declaration>
  </types:enrichment>
</types:mule>